amqmonitoring/__init__.py
amqmonitoring/async_session_gui.py
amqmonitoring/cli.py
amqmonitoring/client.py
amqmonitoring/database.py
amqmonitoring/gui.py
amqmonitoring/main.py
amqmonitoring/monitor.py
amqmonitoring/reader.py
amqmonitoring/session_gui.py
amqmonitoring/session_manager.py
amqmonitoring/utils.py
amqmonitoring-0.2.1.dist-info/METADATA
amqmonitoring-0.2.1.dist-info/WHEEL
amqmonitoring-0.2.1.dist-info/entry_points.txt
amqmonitoring-0.2.1.dist-info/RECORD
