Metadata-Version: 2.4
Name: amqmonitoring
Version: 0.2.1
Summary: RabbitMQ exchange monitoring tool with CLI and GUI interfaces
Requires-Python: >=3.11
Requires-Dist: aio-pika>=9.0.0
Requires-Dist: aiosqlite>=0.20.0
Requires-Dist: pika>=1.3.2
